{
  "configVersion": 1,
  "index": "/index.html",
  "assetGroups": [
    {
      "name": "app",
      "installMode": "prefetch",
      "updateMode": "prefetch",
      "urls": [
        "/es2015-polyfills.44b450db0b1006206bb5.js",
        "/index.html",
        "/main.0b691e8c2e0536e34861.js",
        "/polyfills.8bbb231b43165d65d357.js",
        "/runtime.26209474bfa8dc87a77c.js",
        "/scripts.4b141884c8b3e85769cd.js",
        "/styles.a33e362ce06c66bfd0ba.css",
        "/styles.c370398fddf1e125b70e.js"
      ],
      "patterns": []
    },
    {
      "name": "assets",
      "installMode": "lazy",
      "updateMode": "prefetch",
      "urls": [
        "/assets/bg-masthead.jpg",
        "/assets/david_gwyn.jpeg",
        "/assets/dennis_k.png",
        "/assets/developer_fill.png",
        "/assets/favicon.ico",
        "/assets/gabriele_hunte.png",
        "/assets/heeyeong_kim.png",
        "/assets/logo.png",
        "/assets/minseok_choi.jpeg",
        "/assets/ryan_watson.jpeg",
        "/assets/semy_jin.png",
        "/assets/tyler_trafford.png",
        "/assets/yayun_yang.png",
        "/bg-masthead.17a2aede28655387873e.jpg",
        "/fa-brands-400.2ef8ba3410dcc71578a8.woff",
        "/fa-brands-400.5bf145531213545e03ff.svg",
        "/fa-brands-400.5e2f92123d241cabecf0.woff2",
        "/fa-brands-400.98b6db59be947f563350.ttf",
        "/fa-brands-400.a7b95dbdd87e0c809570.eot",
        "/fa-regular-400.427d721b86fc9c68b2e8.woff",
        "/fa-regular-400.5eb754ab7dbd2fee5623.svg",
        "/fa-regular-400.65b9977aa23185e8964b.ttf",
        "/fa-regular-400.dcce4b7fbd5e895561e1.eot",
        "/fa-regular-400.e6257a726a0cf6ec8c6f.woff2",
        "/fa-solid-900.418dad87601f9c8abd0e.woff2",
        "/fa-solid-900.46e7cec623d8bd790d9f.eot",
        "/fa-solid-900.49279363201ed19a8407.svg",
        "/fa-solid-900.a7140145ebaaf5fb14e4.woff",
        "/fa-solid-900.ff8d9f8adb0d09f11d48.ttf",
        "/glyphicons-halflings-regular.448c34a56d699c29117a.woff2",
        "/glyphicons-halflings-regular.89889688147bd7575d63.svg",
        "/glyphicons-halflings-regular.e18bbf611f2a2e43afc0.ttf",
        "/glyphicons-halflings-regular.f4769f9bdb7466be6508.eot",
        "/glyphicons-halflings-regular.fa2772327f55d8198301.woff"
      ],
      "patterns": []
    }
  ],
  "dataGroups": [],
  "hashTable": {
    "/assets/bg-masthead.jpg": "09ce0aeb5f514d64e5e0cf2f44647cf682d9eaba",
    "/assets/david_gwyn.jpeg": "4a488273b9dbab22ed6cd47fbe6c366f8837c4d9",
    "/assets/dennis_k.png": "3936bbc3b31c57b04e0abf1bffe19a6401770691",
    "/assets/developer_fill.png": "e7639566290f7960c7639b8fd1777a3788893c7c",
    "/assets/favicon.ico": "dab4075a08eb9ce17eb558b0836e391de17c9496",
    "/assets/gabriele_hunte.png": "875662facf274cbb9943c81d215670f97c0665e2",
    "/assets/heeyeong_kim.png": "9f618cc48a051e48ccc575c2775e549d04bdc548",
    "/assets/logo.png": "322d66bc916dd3ccca39cc3ddc15da4612cd4b94",
    "/assets/minseok_choi.jpeg": "59bd5fd1475fb526a695ca5de76dd76b28c20b5b",
    "/assets/ryan_watson.jpeg": "a41c6f26d7484827ea714598d9d32737770e7132",
    "/assets/semy_jin.png": "513d7f58b43dda8c0c3c952a7f7c33251e1ad262",
    "/assets/tyler_trafford.png": "05bd8b3418c8f90da7d4f0b194e2e914caf00352",
    "/assets/yayun_yang.png": "8499d5e092302bbc1ed33dfd436b0c3d42bf67dc",
    "/bg-masthead.17a2aede28655387873e.jpg": "09ce0aeb5f514d64e5e0cf2f44647cf682d9eaba",
    "/es2015-polyfills.44b450db0b1006206bb5.js": "2f388121100fc23553ef172f4227276f96b7a97c",
    "/fa-brands-400.2ef8ba3410dcc71578a8.woff": "e046b8b74b6da1ee3a1910072610de5fc717599f",
    "/fa-brands-400.5bf145531213545e03ff.svg": "44d284802be840d96d26c7f38887925fa83bd383",
    "/fa-brands-400.5e2f92123d241cabecf0.woff2": "7f6c682ade204e641aed8f471064c56b6eddc263",
    "/fa-brands-400.98b6db59be947f563350.ttf": "4f75840965f2020b9e972cf92b0019c17d9e51ed",
    "/fa-brands-400.a7b95dbdd87e0c809570.eot": "1cd2c2b11826ca1e10bc077d18b2f24257bf88a4",
    "/fa-regular-400.427d721b86fc9c68b2e8.woff": "b0b4432c6571662650dc3cbe63fd5ef1eb920b73",
    "/fa-regular-400.5eb754ab7dbd2fee5623.svg": "c514f3c7903cc74638d86bcd635ec00fd55205ce",
    "/fa-regular-400.65b9977aa23185e8964b.ttf": "88a545352247dfbb90281dda98110a8daec8d85e",
    "/fa-regular-400.dcce4b7fbd5e895561e1.eot": "6626847cf66ee47e84d94944b4d01ddb2e3366cb",
    "/fa-regular-400.e6257a726a0cf6ec8c6f.woff2": "8583a4f0dd12e15a48b3395593307a84d971cc33",
    "/fa-solid-900.418dad87601f9c8abd0e.woff2": "a6b003ef506e92d05cde73adf67487d7fd7ec6df",
    "/fa-solid-900.46e7cec623d8bd790d9f.eot": "94be46c754a1415ed221f78136e45449018da0ed",
    "/fa-solid-900.49279363201ed19a8407.svg": "934f021c6fa3aa0310e9eeea25d78a132a204a51",
    "/fa-solid-900.a7140145ebaaf5fb14e4.woff": "964d5b16950adecf14e632adf9270772031ecb9d",
    "/fa-solid-900.ff8d9f8adb0d09f11d48.ttf": "75389055ff16f50e13c46b95da3c59af091f34c1",
    "/glyphicons-halflings-regular.448c34a56d699c29117a.woff2": "ca35b697d99cae4d1b60f2d60fcd37771987eb07",
    "/glyphicons-halflings-regular.89889688147bd7575d63.svg": "de51a8494180a6db074af2dee2383f0a363c5b08",
    "/glyphicons-halflings-regular.e18bbf611f2a2e43afc0.ttf": "44bc1850f570972267b169ae18f1cb06b611ffa2",
    "/glyphicons-halflings-regular.f4769f9bdb7466be6508.eot": "86b6f62b7853e67d3e635f6512a5a5efc58ea3c3",
    "/glyphicons-halflings-regular.fa2772327f55d8198301.woff": "278e49a86e634da6f2a02f3b47dd9d2a8f26210f",
    "/index.html": "f5f20568f7a8f7beb25e3f333cc66a134bb76a98",
    "/main.0b691e8c2e0536e34861.js": "0b579447c205949af73a7d7a36adabed9a4fbc87",
    "/polyfills.8bbb231b43165d65d357.js": "ffa449995bf2eba2ccd0a002417214f7eb75e7b5",
    "/runtime.26209474bfa8dc87a77c.js": "b62956c2192bfe5516d6374e753773901ed50ec5",
    "/scripts.4b141884c8b3e85769cd.js": "ae85ace590676bd96c6d57b985a9663069c99d60",
    "/styles.a33e362ce06c66bfd0ba.css": "19c6a123fe25cfe468e203518bb1619aec00ae36",
    "/styles.c370398fddf1e125b70e.js": "a6a335a0646d2c45411dfe6f88bcd1b006d364c7"
  },
  "navigationUrls": [
    {
      "positive": true,
      "regex": "^\\/.*$"
    },
    {
      "positive": false,
      "regex": "^\\/(?:.+\\/)?[^/]*\\.[^/]*$"
    },
    {
      "positive": false,
      "regex": "^\\/(?:.+\\/)?[^/]*__[^/]*$"
    },
    {
      "positive": false,
      "regex": "^\\/(?:.+\\/)?[^/]*__[^/]*\\/.*$"
    }
  ]
}